xiaoqiangclub/__init__.py
xiaoqiangclub/api/__init__.py
xiaoqiangclub/api/ctfile.py
xiaoqiangclub/api/playwright_codegen.py
xiaoqiangclub/api/ai/__init__.py
xiaoqiangclub/api/ai/big_model.py
xiaoqiangclub/api/ai/chatgpt.py
xiaoqiangclub/api/ai/openai_gemini.py
xiaoqiangclub/api/ai/spark_lite.py
xiaoqiangclub/api/douban/__init__.py
xiaoqiangclub/api/douban/douban_movie_top250.py
xiaoqiangclub/api/douban/douban_wish.py
xiaoqiangclub/api/hao6v/__init__.py
xiaoqiangclub/api/hao6v/hao6v.py
xiaoqiangclub/api/hao6v/season_extractor.py
xiaoqiangclub/api/message_sender/__init__.py
xiaoqiangclub/api/message_sender/an_push_sender.py
xiaoqiangclub/api/message_sender/async_sender.py
xiaoqiangclub/api/message_sender/bark_sender.py
xiaoqiangclub/api/message_sender/config_loader.py
xiaoqiangclub/api/message_sender/dingtalk_sender.py
xiaoqiangclub/api/message_sender/discord_sender.py
xiaoqiangclub/api/message_sender/email_sender.py
xiaoqiangclub/api/message_sender/feishu_sender.py
xiaoqiangclub/api/message_sender/igot_sender.py
xiaoqiangclub/api/message_sender/push_plus_sender.py
xiaoqiangclub/api/message_sender/sender.py
xiaoqiangclub/api/message_sender/telegram_sender.py
xiaoqiangclub/api/message_sender/wechat_sender.py
xiaoqiangclub/api/message_sender/whatsapp_sender.py
xiaoqiangclub/api/stt_asr/__init__.py
xiaoqiangclub/api/stt_asr/stt.py
xiaoqiangclub/api/stt_asr/video_to_audio.py
xiaoqiangclub/api/stt_asr/bk_asr/ASRData.py
xiaoqiangclub/api/stt_asr/bk_asr/BaseASR.py
xiaoqiangclub/api/stt_asr/bk_asr/BcutASR.py
xiaoqiangclub/api/stt_asr/bk_asr/KuaiShouASR.py
xiaoqiangclub/api/stt_asr/bk_asr/__init__.py
xiaoqiangclub/api/stt_asr/bk_asr/example.py
xiaoqiangclub/api/tts/__init__.py
xiaoqiangclub/api/tts/tts_by_edge.py
xiaoqiangclub/api/wechat/__init__.py
xiaoqiangclub/api/wechat/chatbot.py
xiaoqiangclub/api/wechat/wechat_auto_reply.py
xiaoqiangclub/api/xunlei/__init__.py
xiaoqiangclub/api/xunlei/_get_captcha_sign.py
xiaoqiangclub/api/xunlei/xunlei.py
xiaoqiangclub-0.2.12.dist-info/LICENSE
xiaoqiangclub-0.2.12.dist-info/METADATA
xiaoqiangclub-0.2.12.dist-info/WHEEL
xiaoqiangclub-0.2.12.dist-info/entry_points.txt
xiaoqiangclub-0.2.12.dist-info/top_level.txt
xiaoqiangclub-0.2.12.dist-info/RECORD
