Metadata-Version: 2.1
Name: xiaoqiangclub
Version: 0.2.12
Summary: XiaoqiangClub 自用工具包
Home-page: https://gitee.com/xiaoqiangclub/xiaoqiangclub
Author: xiaoqiang
Author-email: xiaoqiangclub@hotmail.com
License: Apache 2.0
Classifier: Programming Language :: Python :: 3
Classifier: License :: OSI Approved :: MIT License
Classifier: Operating System :: OS Independent
Requires-Python: >=3.9
License-File: LICENSE
Requires-Dist: aiofiles==24.1.0
Requires-Dist: aiosqlite==0.20.0
Requires-Dist: apscheduler==3.10.4
Requires-Dist: bencodepy==0.9.5
Requires-Dist: edge-tts==7.0.0
Requires-Dist: fake-useragent==1.5.1
Requires-Dist: fastapi==0.115.5
Requires-Dist: httpx[socks]==0.27.2
Requires-Dist: jinja2==3.1.6
Requires-Dist: moviepy==2.1.2
Requires-Dist: openai==1.59.4
Requires-Dist: parsel==1.9.1
Requires-Dist: pycryptodome==3.21.0
Requires-Dist: pygame==2.6.1
Requires-Dist: python-multipart==0.0.20
Requires-Dist: PyYAML==6.0.1
Requires-Dist: pyzipper==0.3.6
Requires-Dist: redis==5.2.0
Requires-Dist: slowapi==0.1.9
Requires-Dist: sqlitedict==2.1.0
Requires-Dist: tinydb==4.8.2
Requires-Dist: websocket==0.2.1
Requires-Dist: wechatpy==1.8.18
Requires-Dist: zhipuai==2.1.5.20230904
Provides-Extra: playwright
Requires-Dist: playwright; extra == "playwright"
Provides-Extra: windows
Requires-Dist: pywin32; extra == "windows"
Requires-Dist: opencv-python; extra == "windows"
Requires-Dist: pillow; extra == "windows"
Requires-Dist: PyAutoGUI; extra == "windows"
Requires-Dist: pynput; extra == "windows"
Requires-Dist: playwright; extra == "windows"
